player2/__init__.py
player2-0.1.0.dist-info/METADATA
player2-0.1.0.dist-info/WHEEL
player2-0.1.0.dist-info/top_level.txt
player2-0.1.0.dist-info/RECORD
