Metadata-Version: 2.2
Name: player2
Version: 0.1.0
Summary: A namespace package for player2
Home-page: https://player2.game
Author: EAMCVD
Author-email: info@axiom-mc.org
Classifier: Programming Language :: Python :: 3
Classifier: License :: OSI Approved :: MIT License
Classifier: Operating System :: OS Independent
Requires-Python: >=3.6
Dynamic: author
Dynamic: author-email
Dynamic: classifier
Dynamic: description
Dynamic: description-content-type
Dynamic: home-page
Dynamic: requires-python
Dynamic: summary
